pyadvdocx/__init__.py
pyadvdocx/__main__.py
pyadvdocx/text.py
pyadvdocx-0.0.4.dist-info/LICENSE
pyadvdocx-0.0.4.dist-info/METADATA
pyadvdocx-0.0.4.dist-info/WHEEL
pyadvdocx-0.0.4.dist-info/entry_points.txt
pyadvdocx-0.0.4.dist-info/top_level.txt
pyadvdocx-0.0.4.dist-info/RECORD
