Metadata-Version: 2.1
Name: pyadvdocx
Version: 0.0.4
Summary: An open source project inspired from python-docx .
Home-page: https://github.com/SerbanTudor04/PyAdvDocx/
Author: SerbanTudor04
Author-email: SerbanTudor04 <tudor.gabriel.serban@gmail.com>
License: MIT License
Project-URL: Homepage, https://github.com/SerbanTudor04/PyAdvDocx/
Keywords: docx,msoffice,advance
Classifier: License :: OSI Approved :: MIT License
Classifier: Programming Language :: Python
Classifier: Programming Language :: Python :: 3
Requires-Python: >=3.10
License-File: LICENSE
Requires-Dist: python-docx
Requires-Dist: tomli ; python_version < "3.11"
Provides-Extra: dev
Requires-Dist: black ; extra == 'dev'
Requires-Dist: bumpver ; extra == 'dev'
Requires-Dist: isort ; extra == 'dev'
Requires-Dist: pip-tools ; extra == 'dev'
Requires-Dist: pytest ; extra == 'dev'
